eternalegypt/__init__.py
eternalegypt/eternalegypt.py
eternalegypt-0.0.17.dist-info/licenses/LICENSE.txt
eternalegypt-0.0.17.dist-info/METADATA
eternalegypt-0.0.17.dist-info/WHEEL
eternalegypt-0.0.17.dist-info/top_level.txt
eternalegypt-0.0.17.dist-info/RECORD
